total_time/__init__.py
total_time/total_time.py
total_time-0.0.5.dist-info/METADATA
total_time-0.0.5.dist-info/WHEEL
total_time-0.0.5.dist-info/licenses/LICENSE
total_time-0.0.5.dist-info/RECORD
