Metadata-Version: 2.3
Name: total_time
Version: 0.0.5
Summary: A simple timer module to measure your program's elapsed time.
Author: Timothee
Classifier: License :: OSI Approved :: MIT License
Classifier: Operating System :: OS Independent
Classifier: Programming Language :: Python :: 3
Requires-Python: >=3.8
